MySerializer/__init__.py
MySerializer/base.py
MySerializer/lib.py
MySerializer/serialize.py
MySerializer/utils/__init__.py
MySerializer/utils/constants.py
MySerializer/utils/helpers.py
MySerializer/utils/templates.py
ftsnowySerializer-1.0.0.dist-info/METADATA
ftsnowySerializer-1.0.0.dist-info/WHEEL
ftsnowySerializer-1.0.0.dist-info/entry_points.txt
ftsnowySerializer-1.0.0.dist-info/top_level.txt
ftsnowySerializer-1.0.0.dist-info/RECORD
