Metadata-Version: 2.1
Name: ftsnowySerializer
Version: 1.0.0
Summary: Custom-made JSON and XMl Serializer for IGI Lab3.
Author: Daniil Barkovskiy
